motorise/__init__.py
motorise/agent.py
motorise/form.py
motorise/link.py
motorise/page.py
motorise/utils.py
motorise-0.2.0.dist-info/METADATA
motorise-0.2.0.dist-info/WHEEL
motorise-0.2.0.dist-info/top_level.txt
motorise-0.2.0.dist-info/RECORD
