Metadata-Version: 2.1
Name: motorise
Version: 0.2.0
Summary: A toy for automating interaction with websites like mechanize
Home-page: https://github.com/zeuxisoo/python-motorise/
Author: Zeuxis Lo
Author-email: seekstudio@gmail.com
License: BSD
Platform: any
Classifier: Development Status :: 5 - Production/Stable
Classifier: Intended Audience :: Developers
Classifier: License :: OSI Approved :: BSD License
Classifier: Programming Language :: Python
Classifier: Programming Language :: Python :: 3
Classifier: Programming Language :: Python :: 3.7
Classifier: Topic :: Internet
Classifier: Topic :: Internet :: WWW/HTTP
Classifier: Topic :: Internet :: WWW/HTTP :: Browsers
Requires-Dist: requests (==2.20.0)
Requires-Dist: beautifulsoup4 (==4.8.1)
Requires-Dist: pytidylib (==0.3.2)
Requires-Dist: pytest (==5.2.2)
